__init__.py
econo_objects.py
econo_objects-0.0.3.dist-info/LICENSE
econo_objects-0.0.3.dist-info/METADATA
econo_objects-0.0.3.dist-info/WHEEL
econo_objects-0.0.3.dist-info/top_level.txt
econo_objects-0.0.3.dist-info/RECORD
