Metadata-Version: 2.2
Name: econo-objects
Version: 0.0.3
Summary: A simple python package for creating economic models and data objects using FRED API data.
Author-email: Nikhil Sunder <nsunder724@gmail.com>
Maintainer-email: Nikhil Sunder <nsunder724@gmail.com>
License:                     GNU AFFERO GENERAL PUBLIC LICENSE
Project-URL: Repository, https://github.com/nikhilxsunder/econo-objects
Project-URL: Issues, https://github.com/nikhilxsunder/econo-objects/issues
Project-URL: Documentation, https://econo-objects.readthedocs.io/en/
Keywords: fred,federal reserve,economics,econometrics,time series
Classifier: Programming Language :: Python :: 3
Classifier: License :: OSI Approved :: GNU Affero General Public License v3
Classifier: Operating System :: OS Independent
Classifier: Development Status :: 4 - Beta
Classifier: Intended Audience :: Financial and Insurance Industry
Classifier: Topic :: Office/Business :: Financial :: Investment
Requires-Python: >=3.8
License-File: LICENSE
Requires-Dist: fedfred
Requires-Dist: matplotlib
Requires-Dist: pandas
Requires-Dist: numpy
Requires-Dist: scipy
